telefone/__init__.py
telefone/api/__init__.py
telefone/api/abc.py
telefone/api/api.py
telefone/api/request_validator/__init__.py
telefone/api/request_validator/abc.py
telefone/api/request_validator/translate_friendly_types_validator.py
telefone/api/response_validator/__init__.py
telefone/api/response_validator/abc.py
telefone/api/response_validator/telegram_api_error_validator.py
telefone/api/utils/__init__.py
telefone/api/utils/file_util.py
telefone/api/utils/token_util.py
telefone/bot/__init__.py
telefone/bot/abc.py
telefone/bot/blueprint/__init__.py
telefone/bot/blueprint/abc.py
telefone/bot/blueprint/bot.py
telefone/bot/bot.py
telefone/bot/dispatch/__init__.py
telefone/bot/dispatch/handlers/__init__.py
telefone/bot/dispatch/handlers/abc.py
telefone/bot/dispatch/handlers/func.py
telefone/bot/dispatch/labelers/__init__.py
telefone/bot/dispatch/labelers/abc.py
telefone/bot/dispatch/labelers/default.py
telefone/bot/dispatch/middlewares/__init__.py
telefone/bot/dispatch/middlewares/base.py
telefone/bot/dispatch/return_manager/__init__.py
telefone/bot/dispatch/return_manager/abc.py
telefone/bot/dispatch/return_manager/message.py
telefone/bot/dispatch/router/__init__.py
telefone/bot/dispatch/router/abc.py
telefone/bot/dispatch/router/bot.py
telefone/bot/dispatch/view/__init__.py
telefone/bot/dispatch/view/abc.py
telefone/bot/dispatch/view/message.py
telefone/bot/dispatch/view/raw.py
telefone/bot/polling/__init__.py
telefone/bot/polling/abc.py
telefone/bot/polling/bot.py
telefone/bot/rules/__init__.py
telefone/bot/rules/abc.py
telefone/bot/rules/base.py
telefone/bot/rules/callback_query.py
telefone/bot/rules/message.py
telefone/bot/states/__init__.py
telefone/bot/states/dispenser/__init__.py
telefone/bot/states/dispenser/abc.py
telefone/bot/states/dispenser/default.py
telefone/bot/states/types.py
telefone/bot/updates/__init__.py
telefone/bot/updates/base.py
telefone/bot/updates/types.py
telefone/contrib/__init__.py
telefone/contrib/rules/__init__.py
telefone-6.3.1.dist-info/LICENSE
telefone-6.3.1.dist-info/WHEEL
telefone-6.3.1.dist-info/METADATA
telefone-6.3.1.dist-info/RECORD
