Metadata-Version: 2.1
Name: telefone
Version: 6.3.1
Summary: Asynchronous, feature-rich, high performant Telegram Bot API framework for building stunning bots
Home-page: https://pypi.org/project/telefone/
License: MIT
Requires-Python: >=3.8,<4.0
Classifier: License :: OSI Approved :: MIT License
Classifier: Programming Language :: Python :: 3
Classifier: Programming Language :: Python :: 3.10
Classifier: Programming Language :: Python :: 3.8
Classifier: Programming Language :: Python :: 3.9
Provides-Extra: auto-reload
Provides-Extra: better-performance
Requires-Dist: aiohttp (>=3.8.1,<4.0.0)
Requires-Dist: certifi (>=2022.6.15,<2023.0.0)
Requires-Dist: choicelib (>=0.1.5,<0.2.0)
Requires-Dist: orjson (>=3.7.11,<4.0.0); extra == "better-performance"
Requires-Dist: pydantic (>=1.9.0,<2.0.0)
Requires-Dist: typing-extensions (>=4.3.0,<5.0.0)
Requires-Dist: uvloop (>=0.16.0,<0.17.0); extra == "better-performance"
Requires-Dist: watchfiles (>=0.16.0,<0.17.0); extra == "auto-reload"
